Metadata-Version: 1.1
Name: sigdump
Version: 0.0.1
Summary: Use signal to show stacktrace of a Python process
Home-page: https://github.com/c-bata/pysigdump
Author: Masashi Shibata <m.shibata1020@gmail.com>
Author-email: m.shibata1020@gmail.com
License: MIT License
Keywords: process stacktrace garbagecollection
Platform: UNKNOWN
Classifier: Development Status :: 2 - Pre-Alpha
Classifier: Intended Audience :: Developers
Classifier: License :: OSI Approved :: MIT License
Classifier: Programming Language :: Python
Classifier: Programming Language :: Python :: 3
